visual_center/__init__.py
visual_center/polygon.py
visual_center/quadtree.py
visual_center-0.1.2.dist-info/LICENSE
visual_center-0.1.2.dist-info/METADATA
visual_center-0.1.2.dist-info/WHEEL
visual_center-0.1.2.dist-info/top_level.txt
visual_center-0.1.2.dist-info/RECORD
