Metadata-Version: 2.1
Name: visual-center
Version: 0.1.2
Summary: For finding the visual center of a polygon.
Home-page: https://github.com/MatthewLeeCode/visual-center
Author: Matthew Lee
Requires-Python: >=3.10
License-File: LICENSE
Requires-Dist: opencv-python (==4.6.0.66)
